fyn_api_client/__init__.py
fyn_api_client/api_client.py
fyn_api_client/api_response.py
fyn_api_client/configuration.py
fyn_api_client/exceptions.py
fyn_api_client/py.typed
fyn_api_client/rest.py
fyn_api_client/api/__init__.py
fyn_api_client/api/accounts_api.py
fyn_api_client/api/api_api.py
fyn_api_client/api/application_registry_api.py
fyn_api_client/api/auth_api.py
fyn_api_client/api/job_manager_api.py
fyn_api_client/api/runner_manager_api.py
fyn_api_client/models/__init__.py
fyn_api_client/models/app.py
fyn_api_client/models/auth_user_login_create200_response.py
fyn_api_client/models/auth_user_logout_create200_response.py
fyn_api_client/models/job_info.py
fyn_api_client/models/job_info_request.py
fyn_api_client/models/job_info_runner.py
fyn_api_client/models/job_info_runner_request.py
fyn_api_client/models/job_resource.py
fyn_api_client/models/job_resource_request.py
fyn_api_client/models/job_resource_runner.py
fyn_api_client/models/login_request.py
fyn_api_client/models/password_update_request.py
fyn_api_client/models/patched_job_info_request.py
fyn_api_client/models/patched_job_info_runner_request.py
fyn_api_client/models/patched_job_resource_request.py
fyn_api_client/models/patched_runner_info_request.py
fyn_api_client/models/patched_user_request.py
fyn_api_client/models/resource_type_enum.py
fyn_api_client/models/runner_info.py
fyn_api_client/models/runner_info_request.py
fyn_api_client/models/state_enum.py
fyn_api_client/models/status_enum.py
fyn_api_client/models/token_obtain_pair.py
fyn_api_client/models/token_obtain_pair_request.py
fyn_api_client/models/token_refresh.py
fyn_api_client/models/token_refresh_request.py
fyn_api_client/models/token_verify_request.py
fyn_api_client/models/type_enum.py
fyn_api_client/models/user.py
fyn_api_client/models/user_request.py
fyn_api_client-0.0.18.dist-info/METADATA
fyn_api_client-0.0.18.dist-info/WHEEL
fyn_api_client-0.0.18.dist-info/top_level.txt
fyn_api_client-0.0.18.dist-info/RECORD
